fhandleio/__init__.py
fhandleio/fhandleio.py
fhandleio-1.0.1.dist-info/LICENSE
fhandleio-1.0.1.dist-info/METADATA
fhandleio-1.0.1.dist-info/WHEEL
fhandleio-1.0.1.dist-info/top_level.txt
fhandleio-1.0.1.dist-info/RECORD
