Metadata-Version: 2.1
Name: fhandleio
Version: 1.0.1
Summary: Handling files super easily
Home-page: https://devsquaresio.github.io
Author: DevSquares
Author-email: reeyanpeekaboo69@gmail.com
Classifier: Programming Language :: Python :: 3
Classifier: License :: OSI Approved :: MIT License
Classifier: Operating System :: OS Independent
Requires-Python: >=3.7
License-File: LICENSE
